#pragma once
#include "./_.hpp"

namespace jdc
{

    using xOpCode = uint8_t;

    constexpr const xOpCode OP_NOP                 = 0x00;
    constexpr const xOpCode OP_ACONST_NULL         = 0x01;
    constexpr const xOpCode OP_ICONST_M1           = 0x02;
    constexpr const xOpCode OP_ICONST_0            = 0x03;
    constexpr const xOpCode OP_ICONST_1            = 0x04;
    constexpr const xOpCode OP_ICONST_2            = 0x05;
    constexpr const xOpCode OP_ICONST_3            = 0x06;
    constexpr const xOpCode OP_ICONST_4            = 0x07;
    constexpr const xOpCode OP_ICONST_5            = 0x08;
    constexpr const xOpCode OP_LCONST_0            = 0x09;
    constexpr const xOpCode OP_LCONST_1            = 0x0a;
    constexpr const xOpCode OP_FCONST_0            = 0x0b;
    constexpr const xOpCode OP_FCONST_1            = 0x0c;
    constexpr const xOpCode OP_FCONST_2            = 0x0d;
    constexpr const xOpCode OP_DCONST_0            = 0x0e;
    constexpr const xOpCode OP_DCONST_1            = 0x0f;
    constexpr const xOpCode OP_BIPUSH              = 0x10;
    constexpr const xOpCode OP_SIPUSH              = 0x11;
    constexpr const xOpCode OP_LDC                 = 0x12;
    constexpr const xOpCode OP_LDC_W               = 0x13;
    constexpr const xOpCode OP_LDC2_W              = 0x14;
    constexpr const xOpCode OP_ILOAD               = 0x15;
    constexpr const xOpCode OP_LLOAD               = 0x16;
    constexpr const xOpCode OP_FLOAD               = 0x17;
    constexpr const xOpCode OP_DLOAD               = 0x18;
    constexpr const xOpCode OP_ALOAD               = 0x19;
    constexpr const xOpCode OP_ILOAD_0             = 0x1a;
    constexpr const xOpCode OP_ILOAD_1             = 0x1b;
    constexpr const xOpCode OP_ILOAD_2             = 0x1c;
    constexpr const xOpCode OP_ILOAD_3             = 0x1d;
    constexpr const xOpCode OP_LLOAD_0             = 0x1e;
    constexpr const xOpCode OP_LLOAD_1             = 0x1f;
    constexpr const xOpCode OP_LLOAD_2             = 0x20;
    constexpr const xOpCode OP_LLOAD_3             = 0x21;
    constexpr const xOpCode OP_FLOAD_0             = 0x22;
    constexpr const xOpCode OP_FLOAD_1             = 0x23;
    constexpr const xOpCode OP_FLOAD_2             = 0x24;
    constexpr const xOpCode OP_FLOAD_3             = 0x25;
    constexpr const xOpCode OP_DLOAD_0             = 0x26;
    constexpr const xOpCode OP_DLOAD_1             = 0x27;
    constexpr const xOpCode OP_DLOAD_2             = 0x28;
    constexpr const xOpCode OP_DLOAD_3             = 0x29;
    constexpr const xOpCode OP_ALOAD_0             = 0x2a;
    constexpr const xOpCode OP_ALOAD_1             = 0x2b;
    constexpr const xOpCode OP_ALOAD_2             = 0x2c;
    constexpr const xOpCode OP_ALOAD_3             = 0x2d;
    constexpr const xOpCode OP_IALOAD              = 0x2e;
    constexpr const xOpCode OP_LALOAD              = 0x2f;
    constexpr const xOpCode OP_FALOAD              = 0x30;
    constexpr const xOpCode OP_DALOAD              = 0x31;
    constexpr const xOpCode OP_AALOAD              = 0x32;
    constexpr const xOpCode OP_BALOAD              = 0x33;
    constexpr const xOpCode OP_CALOAD              = 0x34;
    constexpr const xOpCode OP_SALOAD              = 0x35;
    constexpr const xOpCode OP_ISTORE              = 0x36;
    constexpr const xOpCode OP_LSTORE              = 0x37;
    constexpr const xOpCode OP_FSTORE              = 0x38;
    constexpr const xOpCode OP_DSTORE              = 0x39;
    constexpr const xOpCode OP_ASTORE              = 0x3a;
    constexpr const xOpCode OP_ISTORE_0            = 0x3b;
    constexpr const xOpCode OP_ISTORE_1            = 0x3c;
    constexpr const xOpCode OP_ISTORE_2            = 0x3d;
    constexpr const xOpCode OP_ISTORE_3            = 0x3e;
    constexpr const xOpCode OP_LSTORE_0            = 0x3f;
    constexpr const xOpCode OP_LSTORE_1            = 0x40;
    constexpr const xOpCode OP_LSTORE_2            = 0x41;
    constexpr const xOpCode OP_LSTORE_3            = 0x42;
    constexpr const xOpCode OP_FSTORE_0            = 0x43;
    constexpr const xOpCode OP_FSTORE_1            = 0x44;
    constexpr const xOpCode OP_FSTORE_2            = 0x45;
    constexpr const xOpCode OP_FSTORE_3            = 0x46;
    constexpr const xOpCode OP_DSTORE_0            = 0x47;
    constexpr const xOpCode OP_DSTORE_1            = 0x48;
    constexpr const xOpCode OP_DSTORE_2            = 0x49;
    constexpr const xOpCode OP_DSTORE_3            = 0x4a;
    constexpr const xOpCode OP_ASTORE_0            = 0x4b;
    constexpr const xOpCode OP_ASTORE_1            = 0x4c;
    constexpr const xOpCode OP_ASTORE_2            = 0x4d;
    constexpr const xOpCode OP_ASTORE_3            = 0x4e;
    constexpr const xOpCode OP_IASTORE             = 0x4f;
    constexpr const xOpCode OP_LASTORE             = 0x50;
    constexpr const xOpCode OP_FASTORE             = 0x51;
    constexpr const xOpCode OP_DASTORE             = 0x52;
    constexpr const xOpCode OP_AASTORE             = 0x53;
    constexpr const xOpCode OP_BASTORE             = 0x54;
    constexpr const xOpCode OP_CASTORE             = 0x55;
    constexpr const xOpCode OP_SASTORE             = 0x56;
    constexpr const xOpCode OP_POP                 = 0x57;
    constexpr const xOpCode OP_POP2                = 0x58;
    constexpr const xOpCode OP_DUP                 = 0x59;
    constexpr const xOpCode OP_DUP_X1              = 0x5a;
    constexpr const xOpCode OP_DUP_X2              = 0x5b;
    constexpr const xOpCode OP_DUP2                = 0x5c;
    constexpr const xOpCode OP_DUP2_X1             = 0x5d;
    constexpr const xOpCode OP_DUP2_X2             = 0x5e;
    constexpr const xOpCode OP_SWAP                = 0x5f;
    constexpr const xOpCode OP_IADD                = 0x60;
    constexpr const xOpCode OP_LADD                = 0x61;
    constexpr const xOpCode OP_FADD                = 0x62;
    constexpr const xOpCode OP_DADD                = 0x63;
    constexpr const xOpCode OP_ISUB                = 0x64;
    constexpr const xOpCode OP_LSUB                = 0x65;
    constexpr const xOpCode OP_FSUB                = 0x66;
    constexpr const xOpCode OP_DSUB                = 0x67;
    constexpr const xOpCode OP_IMUL                = 0x68;
    constexpr const xOpCode OP_LMUL                = 0x69;
    constexpr const xOpCode OP_FMUL                = 0x6a;
    constexpr const xOpCode OP_DMUL                = 0x6b;
    constexpr const xOpCode OP_IDIV                = 0x6c;
    constexpr const xOpCode OP_LDIV                = 0x6d;
    constexpr const xOpCode OP_FDIV                = 0x6e;
    constexpr const xOpCode OP_DDIV                = 0x6f;
    constexpr const xOpCode OP_IREM                = 0x70;
    constexpr const xOpCode OP_LREM                = 0x71;
    constexpr const xOpCode OP_FREM                = 0x72;
    constexpr const xOpCode OP_DREM                = 0x73;
    constexpr const xOpCode OP_INEG                = 0x74;
    constexpr const xOpCode OP_LNEG                = 0x75;
    constexpr const xOpCode OP_FNEG                = 0x76;
    constexpr const xOpCode OP_DNEG                = 0x77;
    constexpr const xOpCode OP_ISHL                = 0x78;
    constexpr const xOpCode OP_LSHL                = 0x79;
    constexpr const xOpCode OP_ISHR                = 0x7a;
    constexpr const xOpCode OP_LSHR                = 0x7b;
    constexpr const xOpCode OP_IUSHR               = 0x7c;
    constexpr const xOpCode OP_LUSHR               = 0x7d;
    constexpr const xOpCode OP_IAND                = 0x7e;
    constexpr const xOpCode OP_LAND                = 0x7f;
    constexpr const xOpCode OP_IOR                 = 0x80;
    constexpr const xOpCode OP_LOR                 = 0x81;
    constexpr const xOpCode OP_IXOR                = 0x82;
    constexpr const xOpCode OP_LXOR                = 0x83;
    constexpr const xOpCode OP_IINC                = 0x84;
    constexpr const xOpCode OP_I2L                 = 0x85;
    constexpr const xOpCode OP_I2F                 = 0x86;
    constexpr const xOpCode OP_I2D                 = 0x87;
    constexpr const xOpCode OP_L2I                 = 0x88;
    constexpr const xOpCode OP_L2F                 = 0x89;
    constexpr const xOpCode OP_L2D                 = 0x8a;
    constexpr const xOpCode OP_F2I                 = 0x8b;
    constexpr const xOpCode OP_F2L                 = 0x8c;
    constexpr const xOpCode OP_F2D                 = 0x8d;
    constexpr const xOpCode OP_D2I                 = 0x8e;
    constexpr const xOpCode OP_D2L                 = 0x8f;
    constexpr const xOpCode OP_D2F                 = 0x90;
    constexpr const xOpCode OP_I2B                 = 0x91;
    constexpr const xOpCode OP_I2C                 = 0x92;
    constexpr const xOpCode OP_I2S                 = 0x93;
    constexpr const xOpCode OP_LCMP                = 0x94;
    constexpr const xOpCode OP_FCMPL               = 0x95;
    constexpr const xOpCode OP_FCMPG               = 0x96;
    constexpr const xOpCode OP_DCMPL               = 0x97;
    constexpr const xOpCode OP_DCMPG               = 0x98;
    constexpr const xOpCode OP_IFEQ                = 0x99;
    constexpr const xOpCode OP_IFNE                = 0x9a;
    constexpr const xOpCode OP_IFLT                = 0x9b;
    constexpr const xOpCode OP_IFGE                = 0x9c;
    constexpr const xOpCode OP_IFGT                = 0x9d;
    constexpr const xOpCode OP_IFLE                = 0x9e;
    constexpr const xOpCode OP_IF_ICMPEQ           = 0x9f;
    constexpr const xOpCode OP_IF_ICMPNE           = 0xa0;
    constexpr const xOpCode OP_IF_ICMPLT           = 0xa1;
    constexpr const xOpCode OP_IF_ICMPGE           = 0xa2;
    constexpr const xOpCode OP_IF_ICMPGT           = 0xa3;
    constexpr const xOpCode OP_IF_ICMPLE           = 0xa4;
    constexpr const xOpCode OP_IF_ACMPEQ           = 0xa5;
    constexpr const xOpCode OP_IF_ACMPNE           = 0xa6;
    constexpr const xOpCode OP_GOTO                = 0xa7;
    constexpr const xOpCode OP_JSR                 = 0xa8;
    constexpr const xOpCode OP_RET                 = 0xa9;
    constexpr const xOpCode OP_TABLESWITCH         = 0xaa;
    constexpr const xOpCode OP_LOOKUPSWITCH        = 0xab;
    constexpr const xOpCode OP_IRETURN             = 0xac;
    constexpr const xOpCode OP_LRETURN             = 0xad;
    constexpr const xOpCode OP_FRETURN             = 0xae;
    constexpr const xOpCode OP_DRETURN             = 0xaf;
    constexpr const xOpCode OP_ARETURN             = 0xb0;
    constexpr const xOpCode OP_RETURN              = 0xb1;
    constexpr const xOpCode OP_GETSTATIC           = 0xb2;
    constexpr const xOpCode OP_PUTSTATIC           = 0xb3;
    constexpr const xOpCode OP_GETFIELD            = 0xb4;
    constexpr const xOpCode OP_PUTFIELD            = 0xb5;
    constexpr const xOpCode OP_INVOKEVIRTUAL       = 0xb6;
    constexpr const xOpCode OP_INVOKESPECIAL       = 0xb7;
    constexpr const xOpCode OP_INVOKESTATIC        = 0xb8;
    constexpr const xOpCode OP_INVOKEINTERFACE     = 0xb9;
    constexpr const xOpCode OP_INVOKEDYNAMIC       = 0xba;
    constexpr const xOpCode OP_NEW                 = 0xbb;
    constexpr const xOpCode OP_NEWARRAY            = 0xbc;
    constexpr const xOpCode OP_ANEWARRAY           = 0xbd;
    constexpr const xOpCode OP_ARRAYLENGTH         = 0xbe;
    constexpr const xOpCode OP_ATHROW              = 0xbf;
    constexpr const xOpCode OP_CHECKCAST           = 0xc0;
    constexpr const xOpCode OP_INSTANCEOF          = 0xc1;
    constexpr const xOpCode OP_MONITORENTER        = 0xc2;
    constexpr const xOpCode OP_MONITOREXIT         = 0xc3;
    constexpr const xOpCode OP_WIDE                = 0xc4;
    constexpr const xOpCode OP_MULTIANEWARRAY      = 0xc5;
    constexpr const xOpCode OP_IFNULL              = 0xc6;
    constexpr const xOpCode OP_IFNONNULL           = 0xc7;
    constexpr const xOpCode OP_GOTO_W              = 0xc8;
    constexpr const xOpCode OP_JSR_W               = 0xc9;
    constexpr const xOpCode OP_BREAKPOINT          = 0xca;

    constexpr const xOpCode OP_RESERVED_impdep_1   = 0xfe; // implementation defined 1
    constexpr const xOpCode OP_RESERVED_impdep_2   = 0xff; // implementation defined 2

    X_GAME_API const char * GetOpName(xOpCode OpCode);
    X_INLINE   size_t GetOpCount() { return 0x00cb; }

}
